flux_sensitivity/__init__.py
flux_sensitivity/critical_rate.py
flux_sensitivity/version.py
flux_sensitivity/differential/__init__.py
flux_sensitivity/differential/scenarios/__init__.py
flux_sensitivity/differential/scenarios/black.py
flux_sensitivity/integral/__init__.py
flux_sensitivity/io/__init__.py
flux_sensitivity/io/gamma_astro_data.py
flux_sensitivity/tests/resources/cta/LICENSE
flux_sensitivity/tests/resources/cta/Prod5-South-20deg-AverageAz-14MSTs37SSTs.1800s-v0.1.fits.gz
flux_sensitivity/tests/resources/cta/README.md
flux_sensitivity/tests/resources/portal/README.md
flux_sensitivity/tests/resources/portal/differential_flux_electron_per_m2_per_sr_per_GeV_per_s.csv
flux_sensitivity/tests/resources/portal/differential_flux_helium_per_m2_per_sr_per_GeV_per_s.csv
flux_sensitivity/tests/resources/portal/differential_flux_proton_per_m2_per_sr_per_GeV_per_s.csv
flux_sensitivity/tests/resources/portal/effective_acceptance_electron_m2_sr.csv
flux_sensitivity/tests/resources/portal/effective_acceptance_electron_m2_sr_absolute_uncertainty.csv
flux_sensitivity/tests/resources/portal/effective_acceptance_helium_m2_sr.csv
flux_sensitivity/tests/resources/portal/effective_acceptance_helium_m2_sr_absolute_uncertainty.csv
flux_sensitivity/tests/resources/portal/effective_acceptance_proton_m2_sr.csv
flux_sensitivity/tests/resources/portal/effective_acceptance_proton_m2_sr_absolute_uncertainty.csv
flux_sensitivity/tests/resources/portal/effective_area_gamma_m2.csv
flux_sensitivity/tests/resources/portal/effective_area_gamma_m2_absolute_uncertainty.csv
flux_sensitivity/tests/resources/portal/energy_bin_edges_GeV.csv
flux_sensitivity/tests/resources/portal/energy_conditional_probability_reco_given_true_ax0true_ax1reco_electron.csv
flux_sensitivity/tests/resources/portal/energy_conditional_probability_reco_given_true_ax0true_ax1reco_electron_au.csv
flux_sensitivity/tests/resources/portal/energy_conditional_probability_reco_given_true_ax0true_ax1reco_gamma.csv
flux_sensitivity_sebastian_achim_mueller-0.0.9.dist-info/licenses/LICENSE
flux_sensitivity_sebastian_achim_mueller-0.0.9.dist-info/METADATA
flux_sensitivity_sebastian_achim_mueller-0.0.9.dist-info/WHEEL
flux_sensitivity_sebastian_achim_mueller-0.0.9.dist-info/top_level.txt
flux_sensitivity_sebastian_achim_mueller-0.0.9.dist-info/RECORD
