Metadata-Version: 2.4
Name: flux_sensitivity_sebastian-achim-mueller
Version: 0.0.9
Summary: Estimate the flux-sensitivity of a point-source either integral or differential w.r.t. energy.
Home-page: https://github.com/cherenkov-plenoscope/flux_sensitivity
Author: Sebastian Achim Mueller
Author-email: sebastian-achim.mueller@mpi-hd.mpg.de
Classifier: Programming Language :: Python :: 3
Classifier: License :: OSI Approved :: MIT License
Classifier: Operating System :: OS Independent
Classifier: Natural Language :: English
Classifier: Intended Audience :: Science/Research
License-File: LICENSE
Requires-Dist: binning_utils_sebastian-achim-mueller>=0.0.5
Requires-Dist: propagate_uncertainties_sebastian-achim-mueller>=0.2.2
Requires-Dist: lima1983analysis_sebastian-achim-mueller>=0.0.4
Dynamic: author
Dynamic: author-email
Dynamic: classifier
Dynamic: description
Dynamic: description-content-type
Dynamic: home-page
Dynamic: license-file
Dynamic: requires-dist
Dynamic: summary
